proxmox_deploy-0.4.0.dist-info/DESCRIPTION.rst
proxmox_deploy-0.4.0.dist-info/METADATA
proxmox_deploy-0.4.0.dist-info/RECORD
proxmox_deploy-0.4.0.dist-info/WHEEL
proxmox_deploy-0.4.0.dist-info/entry_points.txt
proxmox_deploy-0.4.0.dist-info/metadata.json
proxmox_deploy-0.4.0.dist-info/top_level.txt
proxmoxdeploy/__init__.py
proxmoxdeploy/cli.py
proxmoxdeploy/exceptions.py
proxmoxdeploy/proxmox.py
proxmoxdeploy/questions.py
proxmoxdeploy/version.py
proxmoxdeploy/cloudinit/__init__.py
proxmoxdeploy/cloudinit/templates/__init__.py
proxmoxdeploy/cloudinit/templates/meta-data.j2
proxmoxdeploy/cloudinit/templates/user-data.j2
