Metadata-Version: 2.0
Name: proxmox-deploy
Version: 0.4.0
Summary: proxmox-deploy is cli-based deployment tool for Proxmox
Home-page: https://github.com/LordGaav/proxmox-deploy
Author: Nick Douma
Author-email: n.douma@nekoconeko.nl
License: GPLv3
Platform: UNKNOWN
Classifier: Development Status :: 3 - Alpha
Classifier: Environment :: Console
Classifier: Intended Audience :: Developers
Classifier: Intended Audience :: Information Technology
Classifier: Intended Audience :: System Administrators
Classifier: License :: OSI Approved :: GNU General Public License v3 or later (GPLv3+)
Classifier: Operating System :: POSIX :: Linux
Classifier: Operating System :: POSIX :: BSD
Classifier: Operating System :: POSIX
Classifier: Programming Language :: Python :: 2
Classifier: Programming Language :: Python :: 2.7
Classifier: Programming Language :: Python :: 3
Classifier: Programming Language :: Python :: 3.0
Classifier: Programming Language :: Python :: 3.1
Classifier: Programming Language :: Python :: 3.2
Classifier: Programming Language :: Python :: 3.3
Classifier: Programming Language :: Python :: 3.4
Classifier: Programming Language :: Python :: Implementation :: CPython
Classifier: Programming Language :: Python
Classifier: Topic :: System :: Systems Administration
Classifier: Topic :: Utilities
Requires-Dist: proxmoxer
Requires-Dist: openssh-wrapper
Requires-Dist: Jinja2
Requires-Dist: configobj
Requires-Dist: pytz
